setup.py
AditiRai_GBdistributions/Binomialdistribution.py
AditiRai_GBdistributions/Gaussiandistribution.py
AditiRai_GBdistributions/Generaldistribution.py
AditiRai_GBdistributions/__init__.py
AditiRai_GBdistributions.egg-info/PKG-INFO
AditiRai_GBdistributions.egg-info/SOURCES.txt
AditiRai_GBdistributions.egg-info/dependency_links.txt
AditiRai_GBdistributions.egg-info/not-zip-safe
AditiRai_GBdistributions.egg-info/top_level.txt