Metadata-Version: 1.0
Name: AditiRai-GBdistributions
Version: 0.1.1
Summary: Gaussian & Binomial distributions
Home-page: UNKNOWN
Author: Aditi Rai
Author-email: aditi.rai2021@vitstudent.ac.in
License: UNKNOWN
Platform: UNKNOWN
